aoc_cli_go/__init__.py
aoc_cli_go/getter.py
aoc_cli_go/initialiser.py
aoc_cli_go/language.py
aoc_cli_go/local_validations.py
aoc_cli_go/opener.py
aoc_cli_go/runner.py
aoc_cli_go/submitter.py
aoc_cli_go-0.0.2.dist-info/LICENSE
aoc_cli_go-0.0.2.dist-info/METADATA
aoc_cli_go-0.0.2.dist-info/WHEEL
aoc_cli_go-0.0.2.dist-info/entry_points.txt
aoc_cli_go-0.0.2.dist-info/top_level.txt
aoc_cli_go-0.0.2.dist-info/RECORD
